summo/__init__.py
summo/summary.py
summo-0.0.6.dist-info/LICENSE
summo-0.0.6.dist-info/METADATA
summo-0.0.6.dist-info/WHEEL
summo-0.0.6.dist-info/top_level.txt
summo-0.0.6.dist-info/RECORD
