Metadata-Version: 2.1
Name: summo
Version: 0.0.6
Summary: Describe in detail a pandas DataFrame
Author-email: Rafael Sanabria <rafael.d.sanabria@gmail.com>
License: MIT License
Project-URL: repository, https://github.com/rfsan/summo
Keywords: dataframe,describe,statistics
Classifier: Development Status :: 1 - Planning
Classifier: Intended Audience :: Science/Research
Classifier: License :: OSI Approved :: MIT License
Classifier: Programming Language :: Python :: 3.9
Classifier: Programming Language :: Python :: 3.10
Classifier: Programming Language :: Python :: 3.11
Classifier: Topic :: Scientific/Engineering
Requires-Python: >=3.9
License-File: LICENSE
Requires-Dist: pandas (>=2.0.0)
Provides-Extra: dev
Requires-Dist: pytest (>=7.3) ; extra == 'dev'
Requires-Dist: black (>=23.3.0) ; extra == 'dev'
Requires-Dist: ruff (>=0.0.275) ; extra == 'dev'
Provides-Extra: tests
Requires-Dist: pytest (>=7.3) ; extra == 'tests'
Requires-Dist: deepdiff (>=6.3.1) ; extra == 'tests'
Provides-Extra: typing
Requires-Dist: pandas-stubs (>2.0.0) ; extra == 'typing'
